mssql_dataframe/__equality__.py
mssql_dataframe/__init__.py
mssql_dataframe/connect.py
mssql_dataframe/package.py
mssql_dataframe/core/__init__.py
mssql_dataframe/core/conversion.py
mssql_dataframe/core/conversion_rules.py
mssql_dataframe/core/create.py
mssql_dataframe/core/custom_errors.py
mssql_dataframe/core/dynamic.py
mssql_dataframe/core/modify.py
mssql_dataframe/core/read.py
mssql_dataframe/core/write/__init__.py
mssql_dataframe/core/write/_exceptions.py
mssql_dataframe/core/write/insert.py
mssql_dataframe/core/write/merge.py
mssql_dataframe/core/write/update.py
mssql_dataframe/core/write/write.py
mssql_dataframe-3.2.0.dist-info/LICENSE
mssql_dataframe-3.2.0.dist-info/METADATA
mssql_dataframe-3.2.0.dist-info/WHEEL
mssql_dataframe-3.2.0.dist-info/top_level.txt
mssql_dataframe-3.2.0.dist-info/RECORD
