Metadata-Version: 2.1
Name: mssql_dataframe
Version: 3.2.0
Summary: Update, Upsert, and Merge from Python dataframes to SQL Server and Azure SQL database.
Home-page: https://github.com/jwcook23/mssql_dataframe
Author: Jason Cook
Author-email: jasoncook1989@gmail.com
Project-URL: Bug Tracker, https://github.com/jwcook23/mssql_dataframe/issues
Classifier: License :: OSI Approved :: MIT License
Classifier: Operating System :: Microsoft :: Windows
Classifier: Programming Language :: Python :: 3
Requires-Python: >=3.7
License-File: LICENSE
Requires-Dist: pyodbc >=4.0.24
Requires-Dist: pandas >=1.0.0
Requires-Dist: pyarrow
